{"id":44,"name":"Oneylarps","icon":"https://yt3.ggpht.com/QhXePTQKWOwCLDtowJN-fNqgZj-N6hVYqJeSCcIZCQu6SOebGrRF2_oMATvSr2qYAvhGVvBP=s800-c-k-c0x00ffffff-no-rj","banner":"","date":"2026-0","youtube":{"url":"https://www.youtube.com/@Oneylarps","description":"This is a channel\n\nmy instaslop: https://www.instagram.com/oneylarps/\n\nmy twitter: https://x.com/0neyLarps\n","subs":91,"views":1360,"videos":1},"tiktok":"","instagram":"","discord":"","original":"","latestvideo":{"thumbnail":"https://i.ytimg.com/vi/u0xdT05ugXs/hqdefault.jpg","link":"https://www.youtube.com/watch?v=u0xdT05ugXs","title":"OneyLarps Crash Bandicoot - PART 1 - Nondescript Celebrity Island"}}